pubmed_fetcher/__init__.py
pubmed_fetcher/__main__.py
pubmed_fetcher/_init_.py
pubmed_fetcher/cli.py
pubmed_fetcher/fetcher.py
pubmedfetcher-0.1.0.dist-info/entry_points.txt
pubmedfetcher-0.1.0.dist-info/METADATA
pubmedfetcher-0.1.0.dist-info/WHEEL
pubmedfetcher-0.1.0.dist-info/RECORD
