Metadata-Version: 2.3
Name: pubmedfetcher
Version: 0.1.0
Summary: A CLI tool to fetch pubmed articles and filters pharma -affiliated authors.
Author: Pavigowda67
Author-email: pavithrapavithran79@gmail.com
Requires-Python: >=3.10
Classifier: Programming Language :: Python :: 3
Classifier: Programming Language :: Python :: 3.10
Classifier: Programming Language :: Python :: 3.11
Classifier: Programming Language :: Python :: 3.12
Classifier: Programming Language :: Python :: 3.13
Requires-Dist: pandas (>=2.2.3,<3.0.0)
Requires-Dist: requests (>=2.32.3,<3.0.0)
